static_ondisk_kv/__init__.py
static_ondisk_kv/build.py
static_ondisk_kv/order.py
static_ondisk_kv/read.py
static_ondisk_kv-1.1.2.data/data/README.md
static_ondisk_kv-1.1.2.dist-info/LICENSE
static_ondisk_kv-1.1.2.dist-info/METADATA
static_ondisk_kv-1.1.2.dist-info/WHEEL
static_ondisk_kv-1.1.2.dist-info/top_level.txt
static_ondisk_kv-1.1.2.dist-info/RECORD
