Metadata-Version: 2.1
Name: static-ondisk-kv
Version: 1.1.2
Summary: A python template
Home-page: https://github.com/rom1504/static_ondisk_kv
Author: Romain Beaumont
Author-email: romain.rom1@gmail.com
License: MIT
Keywords: machine learning
Platform: UNKNOWN
Classifier: Development Status :: 4 - Beta
Classifier: Intended Audience :: Developers
Classifier: Topic :: Scientific/Engineering :: Artificial Intelligence
Classifier: License :: OSI Approved :: MIT License
Classifier: Programming Language :: Python :: 3.6
Requires-Dist: pyarrow
Requires-Dist: tqdm
Requires-Dist: pandas
Requires-Dist: fire
